result_wrapper/__init__.py
result_wrapper/exceptions.py
result_wrapper/result_wrapper.py
result_wrapper-1.0.0.dist-info/LICENSE
result_wrapper-1.0.0.dist-info/METADATA
result_wrapper-1.0.0.dist-info/WHEEL
result_wrapper-1.0.0.dist-info/top_level.txt
result_wrapper-1.0.0.dist-info/RECORD
