Metadata-Version: 2.1
Name: result-wrapper
Version: 1.0.0
Summary: Result Wrapper
Home-page: https://github.com/tibotix/result_wrapper
Author: Tibotix
Author-email: tizian@seehaus.net
Keywords: exception,result,wrapper
Requires-Python: >=3.6, <4
License-File: LICENSE
Provides-Extra: test
Requires-Dist: pytest ; extra == 'test'
